HISTORY.txt
LICENSE.txt
MANIFEST.in
README.rst
cx_setup.py
doc_open.py
hello_world.py
issue4.py
setup.py
docs/Makefile
docs/api.rst
docs/conf.py
docs/example.py
docs/example_tables.py
docs/gettingstarted.rst
docs/index.rst
docs/make.bat
docs/usage.rst
docs/_static/.empty
docs/_templates/.empty
examples/__init__.py
examples/cable_list_from_schemes.py
examples/cable_tables_to_csv.py
examples/cables_xls_to_autocad.py
examples/calc_cb_place_consumption.py
examples/dev_get_table_info.py
examples/get_names.py
examples/lights.py
pyautocad/__init__.py
pyautocad/api.py
pyautocad/cache.py
pyautocad/compat.py
pyautocad/types.py
pyautocad/utils.py
pyautocad.egg-info/PKG-INFO
pyautocad.egg-info/SOURCES.txt
pyautocad.egg-info/dependency_links.txt
pyautocad.egg-info/requires.txt
pyautocad.egg-info/top_level.txt
pyautocad/contrib/__init__.py
pyautocad/contrib/tables.py
tests/__init__.py
tests/test_api.py
tests/test_cached.py
tests/test_contrib_tables.py
tests/test_some_ideas.py
tests/test_types.py
tests/test_utils.py